awpa/__init__.py
awpa/_utils.py
awpa/_version.py
awpa/btm_matcher.py
awpa/btm_utils.py
awpa/patcomp.py
awpa/pygram.py
awpa/pygram_test.py
awpa/pytree.py
awpa/refactor.py
awpa/gram_pattern/Grammar.txt
awpa/gram_pattern/__init__.py
awpa/gram_pattern/token.py
awpa/gram_py27/Grammar.txt
awpa/gram_py27/__init__.py
awpa/gram_py27/token.py
awpa/gram_py33/Grammar.txt
awpa/gram_py33/__init__.py
awpa/gram_py33/token.py
awpa/gram_py34/Grammar.txt
awpa/gram_py34/__init__.py
awpa/gram_py34/token.py
awpa/gram_py35/Grammar.txt
awpa/gram_py35/__init__.py
awpa/gram_py35/token.py
awpa/gram_py36/Grammar.txt
awpa/gram_py36/__init__.py
awpa/gram_py36/token.py
awpa/gram_py37/Grammar.txt
awpa/gram_py37/__init__.py
awpa/gram_py37/token.py
awpa/pgen2/__init__.py
awpa/pgen2/driver.py
awpa/pgen2/grammar.py
awpa/pgen2/literals.py
awpa/pgen2/parse.py
awpa/pgen2/pgen.py
awpa/pgen2/tokenize.py
awpa-0.19.1.0.dist-info/LICENSE
awpa-0.19.1.0.dist-info/LICENSE.rst
awpa-0.19.1.0.dist-info/METADATA
awpa-0.19.1.0.dist-info/WHEEL
awpa-0.19.1.0.dist-info/top_level.txt
awpa-0.19.1.0.dist-info/RECORD
