Metadata-Version: 2.1
Name: awpa
Version: 0.19.1.0
Summary: A Working Python AST
Home-page: https://github.com/pyga/awpa
Author: Aaron Gallagher
Author-email: _@habnab.it
License: PSF/MIT
Platform: UNKNOWN
